filelist/__init__.py
filelist/filelist.py
filelist-1.1.7.dist-info/DESCRIPTION.rst
filelist-1.1.7.dist-info/METADATA
filelist-1.1.7.dist-info/RECORD
filelist-1.1.7.dist-info/WHEEL
filelist-1.1.7.dist-info/metadata.json
filelist-1.1.7.dist-info/top_level.txt
