Metadata-Version: 2.0
Name: filelist
Version: 1.1.7
Summary: Easily list some files in a directory, and exclude others.
Home-page: https://github.com/Berzeg/filelist
Author: Hashem Berzeg
Author-email: h9.11.2s@gmail.com
License: MIT
Keywords: directory file walk crawl .gitignore .pyignore ignore
Platform: UNKNOWN
Classifier: Development Status :: 3 - Alpha
Classifier: Intended Audience :: Developers
Classifier: Topic :: Software Development
Classifier: License :: OSI Approved :: MIT License
Classifier: Operating System :: OS Independent
Classifier: Programming Language :: Python
Classifier: Programming Language :: Python :: 2
Classifier: Programming Language :: Python :: 2.6
Classifier: Programming Language :: Python :: 2.7
Classifier: Programming Language :: Python :: 3
Classifier: Programming Language :: Python :: 3.2
Classifier: Programming Language :: Python :: 3.3
Classifier: Programming Language :: Python :: 3.4
Classifier: Programming Language :: Python :: 3.5
